{"chunk_definitions":[{"row":60,"row_count":1,"visible":true,"expansion_state":0,"options":{"engine":"r","label":"unnamed-chunk-1","dev":"png"},"document_id":"2289EA9D","chunk_id":"c3bv3er50hcht","chunk_label":"unnamed-chunk-1"},{"row":86,"row_count":1,"visible":true,"expansion_state":0,"options":{"engine":"r","label":"unnamed-chunk-3","dev":"png"},"document_id":"2289EA9D","chunk_id":"cqrwv16mxolp0","chunk_label":"unnamed-chunk-2"},{"row":144,"row_count":1,"visible":true,"expansion_state":0,"options":{"engine":"r","label":"unnamed-chunk-4","dev":"png"},"document_id":"2289EA9D","chunk_id":"c7n7d2y3imlqb","chunk_label":"unnamed-chunk-3"},{"row":153,"row_count":1,"visible":true,"expansion_state":0,"options":{"engine":"r","label":"unnamed-chunk-5","dev":"png"},"document_id":"2289EA9D","chunk_id":"cj868553jefgr","chunk_label":"unnamed-chunk-4"},{"row":209,"row_count":1,"visible":true,"expansion_state":0,"options":{"engine":"r","label":"unnamed-chunk-8","dev":"png"},"document_id":"2289EA9D","chunk_id":"cx094ln84hdsr","chunk_label":"unnamed-chunk-5"},{"row":223,"row_count":1,"visible":true,"expansion_state":0,"options":{"engine":"r","label":"unnamed-chunk-11","dev":"png"},"document_id":"2289EA9D","chunk_id":"cjr39hx9mifj0","chunk_label":"unnamed-chunk-6"},{"row":234,"row_count":1,"visible":true,"expansion_state":0,"options":{"engine":"r","label":"unnamed-chunk-12","dev":"png"},"document_id":"2289EA9D","chunk_id":"c0o294fxw41dn","chunk_label":"unnamed-chunk-7"},{"row":247,"row_count":1,"visible":true,"expansion_state":0,"options":{"engine":"r","label":"unnamed-chunk-16","dev":"png"},"document_id":"2289EA9D","chunk_id":"cvhu7ic08ctug","chunk_label":"unnamed-chunk-8"},{"row":259,"row_count":1,"visible":true,"expansion_state":0,"options":{"engine":"r","label":"unnamed-chunk-17","dev":"png"},"document_id":"2289EA9D","chunk_id":"cyvgucbfyvqvr","chunk_label":"unnamed-chunk-9"},{"row":281,"row_count":1,"visible":true,"expansion_state":0,"options":{"engine":"r","label":"unnamed-chunk-18","dev":"png"},"document_id":"2289EA9D","chunk_id":"cj9myznd0yigc","chunk_label":"unnamed-chunk-10"},{"row":288,"row_count":1,"visible":true,"expansion_state":0,"options":{"engine":"r","label":"unnamed-chunk-19","dev":"png"},"document_id":"2289EA9D","chunk_id":"cjjijei5nbld2","chunk_label":"unnamed-chunk-11"},{"row":300,"row_count":1,"visible":true,"expansion_state":0,"options":{"engine":"r","label":"unnamed-chunk-20","dev":"png"},"document_id":"2289EA9D","chunk_id":"cuj8qt316u0ns","chunk_label":"unnamed-chunk-12"},{"row":327,"row_count":1,"visible":true,"expansion_state":0,"options":{"engine":"r","label":"unnamed-chunk-21","dev":"png"},"document_id":"2289EA9D","chunk_id":"cym67nmtiiewu","chunk_label":"unnamed-chunk-13"},{"row":368,"row_count":1,"visible":true,"expansion_state":0,"options":{"engine":"r","label":"unnamed-chunk-22","dev":"png"},"document_id":"2289EA9D","chunk_id":"chh0su08l7tpd","chunk_label":"unnamed-chunk-14"},{"row":377,"row_count":1,"visible":true,"expansion_state":0,"options":{"engine":"r","label":"unnamed-chunk-23","dev":"png"},"document_id":"2289EA9D","chunk_id":"cuxgza2a85yc3","chunk_label":"unnamed-chunk-15"},{"row":416,"row_count":1,"visible":true,"expansion_state":0,"options":{"engine":"r","label":"unnamed-chunk-24","dev":"png"},"document_id":"2289EA9D","chunk_id":"cxbfw7l5zhadn","chunk_label":"unnamed-chunk-16"},{"row":428,"row_count":1,"visible":true,"expansion_state":0,"options":{"engine":"r","label":"unnamed-chunk-25","dev":"png"},"document_id":"2289EA9D","chunk_id":"cw5kyxd459cc8","chunk_label":"unnamed-chunk-17"},{"row":469,"row_count":1,"visible":true,"expansion_state":0,"options":{"engine":"r","label":"unnamed-chunk-26","dev":"png"},"document_id":"2289EA9D","chunk_id":"celj4jtd7gor5","chunk_label":"unnamed-chunk-18"},{"row":480,"row_count":1,"visible":true,"expansion_state":0,"options":{"engine":"r","label":"unnamed-chunk-30","dev":"png"},"document_id":"2289EA9D","chunk_id":"cb6o6fm91ztld","chunk_label":"unnamed-chunk-19"},{"row":645,"row_count":1,"visible":true,"expansion_state":0,"options":{"engine":"r","label":"unnamed-chunk-33","dev":"png"},"document_id":"2289EA9D","chunk_id":"cr72pehmlyn0l","chunk_label":"unnamed-chunk-22"},{"row":690,"row_count":1,"visible":true,"expansion_state":0,"options":{"engine":"r","label":"unnamed-chunk-35","dev":"png"},"document_id":"2289EA9D","chunk_id":"c04hncdlbufnp","chunk_label":"unnamed-chunk-24"},{"row":667,"row_count":1,"visible":true,"expansion_state":0,"options":{"engine":"r","label":"unnamed-chunk-34","dev":"png"},"document_id":"2289EA9D","chunk_id":"ceqlux9spjsfm","chunk_label":"unnamed-chunk-23"},{"row":714,"row_count":1,"visible":true,"expansion_state":0,"options":{"engine":"r","label":"unnamed-chunk-55","dev":"png"},"document_id":"2289EA9D","chunk_id":"cmmcluqfkokol","chunk_label":"unnamed-chunk-25"},{"row":555,"row_count":1,"visible":true,"expansion_state":0,"options":{"engine":"r","label":"unnamed-chunk-32","dev":"png"},"document_id":"2289EA9D","chunk_id":"cged9b7t2urj2","chunk_label":"unnamed-chunk-21"},{"row":544,"row_count":1,"visible":true,"expansion_state":0,"options":{"engine":"r","label":"unnamed-chunk-31","dev":"png"},"document_id":"2289EA9D","chunk_id":"cdltrkj2t649r","chunk_label":"unnamed-chunk-20"}],"doc_write_time":1731009665}